pyCal2PDF/Generate_PDF.py
pyCal2PDF/__init__.py
pyCal2PDF/pyCalPDF.py
pyCal2PDF-0.0.3.12.data/data/rsc/FirstQuarter.svg
pyCal2PDF-0.0.3.12.data/data/rsc/FullMoon.svg
pyCal2PDF-0.0.3.12.data/data/rsc/LastQuarter.svg
pyCal2PDF-0.0.3.12.data/data/rsc/NewMoon.svg
pyCal2PDF-0.0.3.12.data/data/rsc/Warning.svg
pyCal2PDF-0.0.3.12.dist-info/LICENSE.txt
pyCal2PDF-0.0.3.12.dist-info/METADATA
pyCal2PDF-0.0.3.12.dist-info/WHEEL
pyCal2PDF-0.0.3.12.dist-info/top_level.txt
pyCal2PDF-0.0.3.12.dist-info/RECORD
