Metadata-Version: 2.1
Name: pyCal2PDF
Version: 0.0.3.12
Summary: PDF calendar generator
Home-page: https://github.com/1-annum/pyCal2PDF
Author: Oberron
Author-email: one.annum@gmail.com
License: UNKNOWN
Project-URL: Bug Tracker, https://github.com/1-annum/pyCal2PDF/issues
Platform: UNKNOWN
Classifier: Programming Language :: Python :: 3
Classifier: License :: OSI Approved :: MIT License
Classifier: Operating System :: OS Independent
Requires-Python: >=3.6
License-File: LICENSE.txt
Requires-Dist: reportlab
Requires-Dist: lunardate
Requires-Dist: svglib
Requires-Dist: pyICSParser
